setup.py
dstbn_pack/Binomialdistribution.py
dstbn_pack/Gaussiandistribution.py
dstbn_pack/Generaldistribution.py
dstbn_pack/__init__.py
dstbn_pack.egg-info/PKG-INFO
dstbn_pack.egg-info/SOURCES.txt
dstbn_pack.egg-info/dependency_links.txt
dstbn_pack.egg-info/not-zip-safe
dstbn_pack.egg-info/top_level.txt